odoo/addons/l10n_ro_payment_receipt_report/README.rst
odoo/addons/l10n_ro_payment_receipt_report/__init__.py
odoo/addons/l10n_ro_payment_receipt_report/__manifest__.py
odoo/addons/l10n_ro_payment_receipt_report/data/report_paperformat.xml
odoo/addons/l10n_ro_payment_receipt_report/i18n/l10n_ro_payment_receipt_report.pot
odoo/addons/l10n_ro_payment_receipt_report/i18n/ro.po
odoo/addons/l10n_ro_payment_receipt_report/models/__init__.py
odoo/addons/l10n_ro_payment_receipt_report/models/account_bank_statement_line.py
odoo/addons/l10n_ro_payment_receipt_report/readme/CONTRIBUTORS.md
odoo/addons/l10n_ro_payment_receipt_report/readme/DESCRIPTION.md
odoo/addons/l10n_ro_payment_receipt_report/readme/INSTALL.md
odoo/addons/l10n_ro_payment_receipt_report/readme/USAGE.md
odoo/addons/l10n_ro_payment_receipt_report/static/description/icon.png
odoo/addons/l10n_ro_payment_receipt_report/static/description/icon.svg
odoo/addons/l10n_ro_payment_receipt_report/static/description/index.html
odoo/addons/l10n_ro_payment_receipt_report/views/bank_statement_line_report.xml
odoo/addons/l10n_ro_payment_receipt_report/views/payment_receipt_report.xml
odoo/addons/l10n_ro_payment_receipt_report/views/report_bank_statement_line_payment_template.xml
odoo/addons/l10n_ro_payment_receipt_report/views/report_payment_receipt_template.xml
odoo_addon_l10n_ro_payment_receipt_report-19.0.1.0.0.3.dist-info/METADATA
odoo_addon_l10n_ro_payment_receipt_report-19.0.1.0.0.3.dist-info/WHEEL
odoo_addon_l10n_ro_payment_receipt_report-19.0.1.0.0.3.dist-info/top_level.txt
odoo_addon_l10n_ro_payment_receipt_report-19.0.1.0.0.3.dist-info/RECORD
