Metadata-Version: 2.1
Name: odoo-addon-l10n_ro_payment_receipt_report
Version: 19.0.1.0.0.3
Requires-Dist: num2words>=0.5.8
Requires-Dist: odoo-addon-l10n_ro_payment_to_statement==19.0.*
Requires-Dist: odoo==19.0.*
Summary: Romania - Payment Receipt Report
Home-page: https://github.com/OCA/l10n-romania
License: AGPL-3
Author: Terrabit,NextERP Romania,Odoo Community Association (OCA)
Author-email: support@odoo-community.org
Classifier: Programming Language :: Python
Classifier: Framework :: Odoo
Classifier: Framework :: Odoo :: 19.0
Classifier: License :: OSI Approved :: GNU Affero General Public License v3
Classifier: Development Status :: 6 - Mature
